README.rst
setup.cfg
setup.py
mbq/__init__.py
mbq.atomiq.egg-info/PKG-INFO
mbq.atomiq.egg-info/SOURCES.txt
mbq.atomiq.egg-info/dependency_links.txt
mbq.atomiq.egg-info/not-zip-safe
mbq.atomiq.egg-info/requires.txt
mbq.atomiq.egg-info/top_level.txt
mbq/atomiq/__init__.py
mbq/atomiq/__init__.pyi
mbq/atomiq/__version__.py
mbq/atomiq/admin.py
mbq/atomiq/apps.py
mbq/atomiq/constants.py
mbq/atomiq/consumers.py
mbq/atomiq/exceptions.py
mbq/atomiq/models.py
mbq/atomiq/producers.py
mbq/atomiq/py.typed
mbq/atomiq/test_utils.py
mbq/atomiq/utils.py
mbq/atomiq/management/__init__.py
mbq/atomiq/management/commands/__init__.py
mbq/atomiq/management/commands/atomic_run_consumer.py
mbq/atomiq/migrations/0001_initial_1.py
mbq/atomiq/migrations/0002_auto_20180925_0921.py
mbq/atomiq/migrations/0003_delete_sqstask.py
mbq/atomiq/migrations/__init__.py
tests/__init__.py
tests/settings.py
tests/test_commands.py
tests/test_consumers.py
tests/test_integration.py
tests/test_models.py
tests/test_producers.py
tests/test_test_utils.py
tests/test_utils.py